atrope/__init__.py
atrope/cache.py
atrope/commands.py
atrope/config.py
atrope/endorser.py
atrope/exception.py
atrope/image.py
atrope/importutils.py
atrope/opts.py
atrope/ovf.py
atrope/paths.py
atrope/smime.py
atrope/utils.py
atrope/cmd/__init__.py
atrope/cmd/cli.py
atrope/cmd/test.py
atrope/dispatcher/__init__.py
atrope/dispatcher/base.py
atrope/dispatcher/glance.py
atrope/dispatcher/manager.py
atrope/dispatcher/noop.py
atrope/image_list/__init__.py
atrope/image_list/hepix.py
atrope/image_list/manager.py
atrope/image_list/source.py
atrope/tests/__init__.py
atrope/tests/base.py
atrope/tests/test_atrope.py
atrope-2.0.0.data/data/etc/atrope/atrope-config-generator.conf
atrope-2.0.0.data/data/etc/atrope/atrope.conf.sample
atrope-2.0.0.data/data/etc/atrope/hepix.yaml.sample
atrope-2.0.0.data/data/etc/atrope/voms.json.sample
atrope-2.0.0.dist-info/LICENSE
atrope-2.0.0.dist-info/METADATA
atrope-2.0.0.dist-info/WHEEL
atrope-2.0.0.dist-info/entry_points.txt
atrope-2.0.0.dist-info/pbr.json
atrope-2.0.0.dist-info/top_level.txt
atrope-2.0.0.dist-info/RECORD
